plover_sound/__init__.py
plover_sound/extension.py
plover_sound/icon.svg
plover_sound/keyboard-click.mp3
plover_sound/tool.py
plover_sound-0.0.4.dist-info/LICENSE
plover_sound-0.0.4.dist-info/METADATA
plover_sound-0.0.4.dist-info/WHEEL
plover_sound-0.0.4.dist-info/entry_points.txt
plover_sound-0.0.4.dist-info/top_level.txt
plover_sound-0.0.4.dist-info/zip-safe
plover_sound-0.0.4.dist-info/RECORD
