Metadata-Version: 2.1
Name: plover-sound
Version: 0.0.4
Summary: Plays sound when stroke is registered
Home-page: https://github.com/raoeus/plover-sound
Author: Zach Rice
Author-email: bynxmusic@gmail.com
License: MIT
Keywords: plover plover_plugin
License-File: LICENSE
Requires-Dist: plover[gui_qt] >=4.0.0.rc2
Requires-Dist: pygame >=2.5.2
Requires-Dist: numpy >=1.26.4
